{"data":[{"_id":"vOiR8XoB7WSV3q_kpMGD","_source":{"report_definition":{"report_params":{"report_name":"ai-reasoning-wl-report-def","report_source":"Saved search","description":"","core_params":{"base_url":"/app/discover#/view/ai-resoning-wl-search","report_format":"csv","limit":10000,"time_duration":"PT262992H","saved_search_id":"ai-resoning-wl-search","origin":"http://localhost:5601","excel":true}},"trigger":{"trigger_type":"On demand"},"delivery":{"delivery_type":"Kibana user","delivery_params":{"kibana_recipients":[]}},"time_created":1627550491778,"last_updated":1627550491778,"status":"Active"}}}]}